sthg_fastapi_logs/__init__.py
sthg_fastapi_logs/enumerate.py
sthg_fastapi_logs/exception.py
sthg_fastapi_logs/log_util.py
sthg_fastapi_logs/log_wrapper.py
sthg_fastapi_logs/base_code/__init__.py
sthg_fastapi_logs/base_code/code.py
sthg_fastapi_logs/utils/__init__.py
sthg_fastapi_logs/utils/code_utils.py
sthg_fastapi_logs/utils/exception_utils.py
sthg_fastapi_logs/utils/response_utils.py
sthg_fastapi_logs-0.1.20.dist-info/METADATA
sthg_fastapi_logs-0.1.20.dist-info/WHEEL
sthg_fastapi_logs-0.1.20.dist-info/top_level.txt
sthg_fastapi_logs-0.1.20.dist-info/RECORD
