Metadata-Version: 2.1
Name: sthg_fastapi_logs
Version: 0.1.20
Summary: Python FastApi logs
Home-page: https://github.com/yourusername/your_package_name
Author: DongQing
Author-email: maoyouyu@163.com
Classifier: Development Status :: 3 - Alpha
Classifier: Intended Audience :: Developers
Classifier: License :: OSI Approved :: MIT License
Classifier: Programming Language :: Python :: 3
Classifier: Programming Language :: Python :: 3.7
Classifier: Programming Language :: Python :: 3.8
Classifier: Programming Language :: Python :: 3.9
